anatools/__init__.py
anatools/anacreate.py
anatools/anaclient/__init__.py
anatools/anaclient/_menu.py
anatools/anaclient/agents.py
anatools/anaclient/anaclient.py
anatools/anaclient/analytics.py
anatools/anaclient/annotations.py
anatools/anaclient/api_keys.py
anatools/anaclient/channels.py
anatools/anaclient/datasets.py
anatools/anaclient/editor.py
anatools/anaclient/gan.py
anatools/anaclient/graphs.py
anatools/anaclient/helpers.py
anatools/anaclient/image.py
anatools/anaclient/inpaint.py
anatools/anaclient/llm.py
anatools/anaclient/ml.py
anatools/anaclient/organizations.py
anatools/anaclient/preview.py
anatools/anaclient/rules.py
anatools/anaclient/services.py
anatools/anaclient/umap.py
anatools/anaclient/volumes.py
anatools/anaclient/workspaces.py
anatools/anaclient/api/__init__.py
anatools/anaclient/api/analytics.py
anatools/anaclient/api/annotations.py
anatools/anaclient/api/api.py
anatools/anaclient/api/api_keys.py
anatools/anaclient/api/channels.py
anatools/anaclient/api/datasets.py
anatools/anaclient/api/editor.py
anatools/anaclient/api/gan.py
anatools/anaclient/api/graphs.py
anatools/anaclient/api/handlers.py
anatools/anaclient/api/image.py
anatools/anaclient/api/inpaint.py
anatools/anaclient/api/introspection.py
anatools/anaclient/api/llm.py
anatools/anaclient/api/members.py
anatools/anaclient/api/ml.py
anatools/anaclient/api/organizations.py
anatools/anaclient/api/preview.py
anatools/anaclient/api/rules.py
anatools/anaclient/api/services.py
anatools/anaclient/api/umap.py
anatools/anaclient/api/volumes.py
anatools/anaclient/api/workspaces.py
anatools/anaclient/tests/__init__.py
anatools/anaclient/tests/agents_test.py
anatools/anaclient/tests/anaclient_test.py
anatools/anaclient/tests/analytics_test.py
anatools/anaclient/tests/annotations_test.py
anatools/anaclient/tests/api_keys_test.py
anatools/anaclient/tests/channels_test.py
anatools/anaclient/tests/datasets_test.py
anatools/anaclient/tests/editor_test.py
anatools/anaclient/tests/gan_test.py
anatools-5.1.28.dist-info/licenses/LICENSE
anatools-5.1.28.dist-info/METADATA
anatools-5.1.28.dist-info/WHEEL
anatools-5.1.28.dist-info/entry_points.txt
anatools-5.1.28.dist-info/top_level.txt
anatools-5.1.28.dist-info/RECORD
